{
  "invisible": false,
  "key": "outer",
  "hidden": false,
  "orientation": "vertical",
  "label": "Form",
  "hideLabel": true,
  "component": "form",
  "components": [
    {
      "invisible": false,
      "hidden": false,
      "valueKey": "$",
      "label": "Dev Tools",
      "hideLabel": false,
      "component": "dev-tools",
      "components": []
    },
    {
      "size": "default",
      "invisible": false,
      "hidden": false,
      "valueKey": "value",
      "label": "Number",
      "hideLabel": false,
      "component": "number-input"
    }
  ]
}
